numoptml/__init__.py
numoptml/optimizers/__init__.py
numoptml/optimizers/gradient_descent.py
numoptml/optimizers/newton_method.py
numoptml/utils/__init__.py
numoptml/utils/line_search.py
numoptml-0.1.1.dist-info/METADATA
numoptml-0.1.1.dist-info/WHEEL
numoptml-0.1.1.dist-info/top_level.txt
numoptml-0.1.1.dist-info/RECORD
