Metadata-Version: 2.4
Name: numoptml
Version: 0.1.1
Summary: Численные методы оптимизации для машинного обучения и автоматизации ИИ
Author: Егор
Requires-Python: >=3.7
Requires-Dist: numpy
Dynamic: author
Dynamic: description
Dynamic: description-content-type
Dynamic: requires-dist
Dynamic: requires-python
Dynamic: summary
